Metadata-Version: 2.1
Name: neste-braces
Version: 1.0.0
Summary: Desciption for neste here
Home-page: https://github.com/vivainio/neste
Author: Ville M. Vainio
Author-email: ville.vainio@basware.com
License-File: LICENSE
